LICENSE
MANIFEST.in
README.md
pyproject.toml
setup.py
src/SuperPang.egg-info/PKG-INFO
src/SuperPang.egg-info/SOURCES.txt
src/SuperPang.egg-info/dependency_links.txt
src/SuperPang.egg-info/entry_points.txt
src/SuperPang.egg-info/requires.txt
src/SuperPang.egg-info/top_level.txt
src/superpang/VERSION
src/superpang/__init__.py
src/superpang/lib/Assembler.py
src/superpang/lib/Compressor.pyx
src/superpang/lib/__init__.py
src/superpang/lib/cutils.pyx
src/superpang/lib/utils.py
src/superpang/lib/vtools.pyx
src/superpang/scripts/SuperPang.py
src/superpang/scripts/__init__.py
src/superpang/scripts/condense-edges.py
src/superpang/scripts/homogenize.py
src/superpang/scripts/test-SuperPang.py
src/superpang/scripts/test_SuperPang.py
src/superpang/test_data/2636415981.fna
src/superpang/test_data/2636416036.fna
src/superpang/test_data/2636416061.fna
src/superpang/test_data/2636416062.fna
src/superpang/test_data/2639762512.fna
src/superpang/test_data/2639762514.fna
src/superpang/test_data/2639762515.fna
src/superpang/test_data/2639762516.fna
src/superpang/test_data/2844342787.fna