Metadata-Version: 2.1
Name: SuperPang
Version: 1.3.0.post1
Summary: Non-redundant pangenome assemblies from multiple genomes or bins
Author-email: Fernando Puente-Sánchez <fernando.puente.sanchez@slu.se>
License: BSD 3-Clause License
Project-URL: Homepage, https://github.com/fpusan/SuperPang
Project-URL: Bug Tracker, https://github.com/fpusan/SuperPang/issues
Keywords: bioinformatics,assembly,metagenomics,microbial-genomics,genomics
Classifier: Programming Language :: Python :: 3
Classifier: License :: OSI Approved :: BSD License
Classifier: Operating System :: OS Independent
Classifier: Intended Audience :: Science/Research
Classifier: Topic :: Scientific/Engineering :: Bio-Informatics
Requires-Python: >=3.8
License-File: LICENSE
Requires-Dist: numpy
Requires-Dist: mOTUlizer==0.2.4
Requires-Dist: mappy
Requires-Dist: speedict
